{
  "symbol": {
    "id": "300750",
    "name": "宁德时代"
  },
  "date": "2025-12-25",
  "updated_at": "2026-02-28 21:05",
  "is_stale": false,
  "agents": {
    "status": "unavailable",
    "reason": "price-only stub"
  },
  "plans": {
    "status": "unavailable",
    "reason": "price-only stub"
  },
  "sentiment": {
    "index": 0.0,
    "band": "neutral",
    "counts": {
      "bull": 0,
      "bear": 0,
      "neutral": 0
    },
    "news_total": 0
  },
  "price": {
    "status": "ok",
    "open": 374.21,
    "high": 374.21,
    "low": 369.12,
    "close": 373.01,
    "volume": 203431,
    "open_interest": 0,
    "date": "2025-12-25",
    "is_stale": false,
    "pct_change": -0.69
  },
  "news": [],
  "kline": [],
  "extras": {
    "status": "missing",
    "asof": "2025-12-25",
    "modules": {}
  }
}