{
  "symbol": {
    "id": "gold",
    "name": "黄金"
  },
  "updated_at": "2026-03-13 08:52",
  "asof": "2026-03-12",
  "inventory": {
    "status": "unavailable",
    "hint": "仓单/库存（无数据或接口异常：ValueError）",
    "series": [],
    "summary": null
  },
  "spot_basis": {
    "status": "ok",
    "hint": "现货/基差（AKShare futures_spot_price）",
    "series": [
      {
        "date": "2026-02-24",
        "spot_price": 1148.18,
        "dom_basis": 3.3599999999999,
        "dom_basis_rate": 0.002926370429723546,
        "dom_contract": null,
        "dom_contract_price": null
      },
      {
        "date": "2026-03-04",
        "spot_price": 1186.43,
        "dom_basis": -33.37000000000012,
        "dom_basis_rate": -0.0281263959947069,
        "dom_contract": null,
        "dom_contract_price": null
      },
      {
        "date": "2026-03-05",
        "spot_price": 1154.46,
        "dom_basis": -2.4600000000000364,
        "dom_basis_rate": -0.002130866379086327,
        "dom_contract": null,
        "dom_contract_price": null
      },
      {
        "date": "2026-03-06",
        "spot_price": 1142.27,
        "dom_basis": -1.4700000000000273,
        "dom_basis_rate": -0.0012869111506036424,
        "dom_contract": null,
        "dom_contract_price": null
      },
      {
        "date": "2026-03-09",
        "spot_price": 1138.14,
        "dom_basis": 5.399999999999864,
        "dom_basis_rate": 0.004744583267436209,
        "dom_contract": null,
        "dom_contract_price": null
      },
      {
        "date": "2026-03-10",
        "spot_price": 1148.23,
        "dom_basis": 4.930000000000064,
        "dom_basis_rate": 0.004293564878116829,
        "dom_contract": null,
        "dom_contract_price": null
      },
      {
        "date": "2026-03-11",
        "spot_price": 1151.21,
        "dom_basis": 4.309999999999945,
        "dom_basis_rate": 0.0037438868668617786,
        "dom_contract": null,
        "dom_contract_price": null
      },
      {
        "date": "2026-03-12",
        "spot_price": 1146.0,
        "dom_basis": 5.519999999999982,
        "dom_basis_rate": 0.004816753926701445,
        "dom_contract": null,
        "dom_contract_price": null
      }
    ],
    "summary": "spot_price=1146.0 · dom_basis=5.519999999999982 · dom_basis_rate=0.004816753926701445"
  },
  "roll_yield": {
    "status": "ok",
    "hint": "展期收益率（AKShare get_roll_yield）",
    "series": [
      {
        "date": "2026-02-24",
        "roll_yield": -0.017289277342982152,
        "near_by": "AU2604",
        "deferred": "AU2606"
      },
      {
        "date": "2026-02-25",
        "roll_yield": -0.0170729706591654,
        "near_by": "AU2604",
        "deferred": "AU2606"
      },
      {
        "date": "2026-02-26",
        "roll_yield": -0.018915098092317516,
        "near_by": "AU2604",
        "deferred": "AU2606"
      },
      {
        "date": "2026-02-27",
        "roll_yield": -0.017953772029528157,
        "near_by": "AU2604",
        "deferred": "AU2606"
      },
      {
        "date": "2026-03-02",
        "roll_yield": -0.01691537599336817,
        "near_by": "AU2604",
        "deferred": "AU2606"
      },
      {
        "date": "2026-03-03",
        "roll_yield": -0.01713287582040603,
        "near_by": "AU2604",
        "deferred": "AU2606"
      },
      {
        "date": "2026-03-04",
        "roll_yield": -0.016316925431619195,
        "near_by": "AU2604",
        "deferred": "AU2606"
      },
      {
        "date": "2026-03-05",
        "roll_yield": -0.01591637041651273,
        "near_by": "AU2604",
        "deferred": "AU2606"
      },
      {
        "date": "2026-03-06",
        "roll_yield": -0.017540954487354616,
        "near_by": "AU2604",
        "deferred": "AU2606"
      },
      {
        "date": "2026-03-09",
        "roll_yield": -0.018602710716392166,
        "near_by": "AU2604",
        "deferred": "AU2606"
      },
      {
        "date": "2026-03-10",
        "roll_yield": -0.01646434628698528,
        "near_by": "AU2604",
        "deferred": "AU2606"
      },
      {
        "date": "2026-03-11",
        "roll_yield": -0.018409548570439548,
        "near_by": "AU2604",
        "deferred": "AU2606"
      },
      {
        "date": "2026-03-12",
        "roll_yield": -0.017846439958367852,
        "near_by": "AU2604",
        "deferred": "AU2606"
      }
    ],
    "summary": "roll_yield=-0.017846439958367852 · near_by=AU2604 · deferred=AU2606"
  },
  "positions_rank": {
    "status": "ok",
    "hint": "会员持仓/成交排名（AKShare get_rank_sum_daily）",
    "series": [
      {
        "date": "2026-02-24",
        "long": null,
        "short": null,
        "net": null,
        "volume": null,
        "rows": 6
      },
      {
        "date": "2026-02-25",
        "long": null,
        "short": null,
        "net": null,
        "volume": null,
        "rows": 5
      },
      {
        "date": "2026-02-26",
        "long": null,
        "short": null,
        "net": null,
        "volume": null,
        "rows": 5
      },
      {
        "date": "2026-02-27",
        "long": null,
        "short": null,
        "net": null,
        "volume": null,
        "rows": 5
      },
      {
        "date": "2026-03-02",
        "long": null,
        "short": null,
        "net": null,
        "volume": null,
        "rows": 6
      },
      {
        "date": "2026-03-03",
        "long": null,
        "short": null,
        "net": null,
        "volume": null,
        "rows": 6
      },
      {
        "date": "2026-03-04",
        "long": null,
        "short": null,
        "net": null,
        "volume": null,
        "rows": 6
      },
      {
        "date": "2026-03-05",
        "long": null,
        "short": null,
        "net": null,
        "volume": null,
        "rows": 6
      },
      {
        "date": "2026-03-06",
        "long": null,
        "short": null,
        "net": null,
        "volume": null,
        "rows": 6
      },
      {
        "date": "2026-03-09",
        "long": null,
        "short": null,
        "net": null,
        "volume": null,
        "rows": 6
      },
      {
        "date": "2026-03-10",
        "long": null,
        "short": null,
        "net": null,
        "volume": null,
        "rows": 6
      },
      {
        "date": "2026-03-11",
        "long": null,
        "short": null,
        "net": null,
        "volume": null,
        "rows": 6
      },
      {
        "date": "2026-03-12",
        "long": null,
        "short": null,
        "net": null,
        "volume": null,
        "rows": 6
      }
    ],
    "latest_preview": [
      {
        "symbol": "AU2604",
        "variety": "AU",
        "vol_top5": 157045.0,
        "vol_chg_top5": -4168.0,
        "long_open_interest_top5": 34734.0,
        "long_open_interest_chg_top5": -1873.0,
        "short_open_interest_top5": 12967.0,
        "short_open_interest_chg_top5": -43.0,
        "vol_top10": 201956.0,
        "vol_chg_top10": -9217.0,
        "long_open_interest_top10": 48906.0,
        "long_open_interest_chg_top10": -2556.0,
        "short_open_interest_top10": 15871.0,
        "short_open_interest_chg_top10": -81.0,
        "vol_top15": 227654.0,
        "vol_chg_top15": -14404.0,
        "long_open_interest_top15": 59285.0,
        "long_open_interest_chg_top15": -3123.0,
        "short_open_interest_top15": 17729.0,
        "short_open_interest_chg_top15": -84.0,
        "vol_top20": 244428.0,
        "vol_chg_top20": -18497.0,
        "long_open_interest_top20": 66178.0,
        "long_open_interest_chg_top20": -3407.0,
        "short_open_interest_top20": 19112.0,
        "short_open_interest_chg_top20": -41.0,
        "date": "20260312"
      },
      {
        "symbol": "AU2608",
        "variety": "AU",
        "vol_top5": 12528.0,
        "vol_chg_top5": -8223.0,
        "long_open_interest_top5": 12815.0,
        "long_open_interest_chg_top5": 69.0,
        "short_open_interest_top5": 1783.0,
        "short_open_interest_chg_top5": 458.0,
        "vol_top10": 16851.0,
        "vol_chg_top10": -11280.0,
        "long_open_interest_top10": 17045.0,
        "long_open_interest_chg_top10": -314.0,
        "short_open_interest_top10": 2636.0,
        "short_open_interest_chg_top10": 545.0,
        "vol_top15": 18070.0,
        "vol_chg_top15": -12524.0,
        "long_open_interest_top15": 19170.0,
        "long_open_interest_chg_top15": -343.0,
        "short_open_interest_top15": 2992.0,
        "short_open_interest_chg_top15": 633.0,
        "vol_top20": 18961.0,
        "vol_chg_top20": -13718.0,
        "long_open_interest_top20": 20569.0,
        "long_open_interest_chg_top20": -387.0,
        "short_open_interest_top20": 3242.0,
        "short_open_interest_chg_top20": 698.0,
        "date": "20260312"
      },
      {
        "symbol": "AU2606",
        "variety": "AU",
        "vol_top5": 62830.0,
        "vol_chg_top5": -9249.0,
        "long_open_interest_top5": 44653.0,
        "long_open_interest_chg_top5": 2257.0,
        "short_open_interest_top5": 12065.0,
        "short_open_interest_chg_top5": -397.0,
        "vol_top10": 81170.0,
        "vol_chg_top10": -13283.0,
        "long_open_interest_top10": 60723.0,
        "long_open_interest_chg_top10": 2624.0,
        "short_open_interest_top10": 16431.0,
        "short_open_interest_chg_top10": -486.0,
        "vol_top15": 89638.0,
        "vol_chg_top15": -16068.0,
        "long_open_interest_top15": 73007.0,
        "long_open_interest_chg_top15": 2665.0,
        "short_open_interest_top15": 19011.0,
        "short_open_interest_chg_top15": -321.0,
        "vol_top20": 95888.0,
        "vol_chg_top20": -14974.0,
        "long_open_interest_top20": 82612.0,
        "long_open_interest_chg_top20": 2906.0,
        "short_open_interest_top20": 20521.0,
        "short_open_interest_chg_top20": -385.0,
        "date": "20260312"
      },
      {
        "symbol": "AU2603",
        "variety": "AU",
        "vol_top5": 39.0,
        "vol_chg_top5": 39.0,
        "long_open_interest_top5": 762.0,
        "long_open_interest_chg_top5": 0.0,
        "short_open_interest_top5": 741.0,
        "short_open_interest_chg_top5": 9.0,
        "vol_top10": 42.0,
        "vol_chg_top10": 42.0,
        "long_open_interest_top10": 762.0,
        "long_open_interest_chg_top10": 0.0,
        "short_open_interest_top10": 741.0,
        "short_open_interest_chg_top10": 9.0,
        "vol_top15": 42.0,
        "vol_chg_top15": 42.0,
        "long_open_interest_top15": 762.0,
        "long_open_interest_chg_top15": 0.0,
        "short_open_interest_top15": 741.0,
        "short_open_interest_chg_top15": 9.0,
        "vol_top20": 42.0,
        "vol_chg_top20": 42.0,
        "long_open_interest_top20": 762.0,
        "long_open_interest_chg_top20": 0.0,
        "short_open_interest_top20": 741.0,
        "short_open_interest_chg_top20": 9.0,
        "date": "20260312"
      },
      {
        "symbol": "AU2610",
        "variety": "AU",
        "vol_top5": 5071.0,
        "vol_chg_top5": -607.0,
        "long_open_interest_top5": 7198.0,
        "long_open_interest_chg_top5": 186.0,
        "short_open_interest_top5": 746.0,
        "short_open_interest_chg_top5": 17.0,
        "vol_top10": 6419.0,
        "vol_chg_top10": -1219.0,
        "long_open_interest_top10": 9514.0,
        "long_open_interest_chg_top10": 210.0,
        "short_open_interest_top10": 1035.0,
        "short_open_interest_chg_top10": -2.0,
        "vol_top15": 6983.0,
        "vol_chg_top15": -1357.0,
        "long_open_interest_top15": 10592.0,
        "long_open_interest_chg_top15": 199.0,
        "short_open_interest_top15": 1173.0,
        "short_open_interest_chg_top15": 1.0,
        "vol_top20": 7399.0,
        "vol_chg_top20": -1373.0,
        "long_open_interest_top20": 11358.0,
        "long_open_interest_chg_top20": 234.0,
        "short_open_interest_top20": 1231.0,
        "short_open_interest_chg_top20": 6.0,
        "date": "20260312"
      },
      {
        "symbol": "AU",
        "variety": "AU",
        "vol_top5": 237513.0,
        "vol_chg_top5": -22208.0,
        "long_open_interest_top5": 100162.0,
        "long_open_interest_chg_top5": 639.0,
        "short_open_interest_top5": 28302.0,
        "short_open_interest_chg_top5": 44.0,
        "vol_top10": 306438.0,
        "vol_chg_top10": -34957.0,
        "long_open_interest_top10": 136950.0,
        "long_open_interest_chg_top10": -36.0,
        "short_open_interest_top10": 36714.0,
        "short_open_interest_chg_top10": -15.0,
        "vol_top15": 342387.0,
        "vol_chg_top15": -44311.0,
        "long_open_interest_top15": 162816.0,
        "long_open_interest_chg_top15": -602.0,
        "short_open_interest_top15": 41646.0,
        "short_open_interest_chg_top15": 238.0,
        "vol_top20": 366718.0,
        "vol_chg_top20": -48520.0,
        "long_open_interest_top20": 181479.0,
        "long_open_interest_chg_top20": -654.0,
        "short_open_interest_top20": 44847.0,
        "short_open_interest_chg_top20": 287.0,
        "date": "20260312"
      }
    ],
    "summary": null
  }
}